mjeffryes_hackweek/__init__.py
mjeffryes_hackweek/_utilities.py
mjeffryes_hackweek/hello_component.py
mjeffryes_hackweek/hello_world.py
mjeffryes_hackweek/provider.py
mjeffryes_hackweek/pulumi-plugin.json
mjeffryes_hackweek/py.typed
mjeffryes_hackweek-0.0.0.dist-info/METADATA
mjeffryes_hackweek-0.0.0.dist-info/WHEEL
mjeffryes_hackweek-0.0.0.dist-info/top_level.txt
mjeffryes_hackweek-0.0.0.dist-info/RECORD
