Metadata-Version: 2.4
Name: mjeffryes_hackweek
Version: 0.0.0
Requires-Python: >=3.9
Requires-Dist: parver>=0.2.1
Requires-Dist: pulumi<4.0.0,>=3.142.0
Requires-Dist: semver>=2.8.1
Requires-Dist: typing-extensions<5,>=4.11; python_version < "3.11"
Dynamic: description
Dynamic: description-content-type
Dynamic: requires-dist
Dynamic: requires-python
